hypersonic/__init__.py
hypersonic/__main__.py
hypersonic/hy.py
hypersonic_eda-0.1.3.dist-info/licenses/LICENSE
hypersonic_eda-0.1.3.dist-info/METADATA
hypersonic_eda-0.1.3.dist-info/WHEEL
hypersonic_eda-0.1.3.dist-info/entry_points.txt
hypersonic_eda-0.1.3.dist-info/top_level.txt
hypersonic_eda-0.1.3.dist-info/RECORD
