Metadata-Version: 2.4
Name: hypersonic-eda
Version: 0.1.3
Summary: Generate structured EDA notebooks from datasets.
Author: Krish Ambady
License: MIT
Project-URL: Homepage, https://github.com/UnniAmbady/Hypersonic_EDA
Project-URL: Issues, https://github.com/UnniAmbady/Hypersonic_EDA/issues
Keywords: EDA,notebook,pandas,matplotlib,sqlite
Classifier: Programming Language :: Python :: 3
Classifier: Operating System :: OS Independent
Requires-Python: >=3.9
License-File: LICENSE
Requires-Dist: nbformat>=5.0.0
Requires-Dist: pandas>=1.5.0
Requires-Dist: matplotlib>=3.6.0
Requires-Dist: numpy>=1.23.0
Requires-Dist: requests>=2.28.0
Dynamic: license-file
